{"name":"数组去重","slug":"数组去重","count":1,"postlist":[{"title":"JS含复杂数据类型的数组去重","uid":"27d9c66674931c392080703751c9e35c","slug":"article-01","date":"2022-04-12T06:31:47.000Z","updated":"2022-04-17T11:31:01.100Z","comments":true,"path":"api/articles/article-01.json","keywords":null,"cover":null,"text":"filter + hasOwnProperty + JSON.stringifyfunction unique(arr) &#123; let obj &#x3D; &#123;&#125; return arr.filter((item, index) &#x3D;&gt; &...","link":"","photos":[],"count_time":{"symbolsCount":320,"symbolsTime":"1 mins."},"categories":[{"name":"JAVASCRIPT","slug":"JAVASCRIPT","count":2,"path":"api/categories/JAVASCRIPT.json"}],"tags":[{"name":"数组去重","slug":"数组去重","count":1,"path":"api/tags/数组去重.json"}],"author":{"name":"AliceAllen","slug":"blog-author","avatar":"https://s3.bmp.ovh/imgs/2022/04/17/41ef9adb1a33f91e.jpeg","link":"/","description":"<b>欢迎来到小许的博客</b> <br /><br /><b>一位正在重塑知识的技术人</b> <br /><br><b>日常分享开发过程中遇到的问题</b>","socials":{"github":"","twitter":"","stackoverflow":"","wechat":"","qq":"","weibo":"","zhihu":"","csdn":"","juejin":"","customs":{}}},"feature":true}]}